worm/__init__.py
worm/mapper.py
worm/persistence.py
worm/query.py
worm/adapters/__init__.py
worm/adapters/csv.py
worm/adapters/genericsql.py
worm/engines/__init__.py
worm/engines/csv.py
worm/engines/psycopg2.py
worm/engines/sqlite3.py
worm_dao-0.1.4.dist-info/DESCRIPTION.rst
worm_dao-0.1.4.dist-info/METADATA
worm_dao-0.1.4.dist-info/RECORD
worm_dao-0.1.4.dist-info/WHEEL
worm_dao-0.1.4.dist-info/metadata.json
worm_dao-0.1.4.dist-info/top_level.txt
worm_dao-0.1.4.dist-info/zip-safe
