Metadata-Version: 2.0
Name: worm-dao
Version: 0.1.4
Summary: Worst or wonderful DAO library
Home-page: https://github.com/marcinn/worm
Author: Marcin Nowak
Author-email: marcin.j.nowak@gmail.com
License: UNKNOWN
Keywords: dao orm database
Platform: UNKNOWN
Classifier: Development Status :: 2 - Pre-Alpha
Classifier: License :: OSI Approved :: BSD License
Classifier: Operating System :: OS Independent
Classifier: Programming Language :: Python
Classifier: Programming Language :: Python :: 2.7
Classifier: Topic :: Database :: Front-Ends
Classifier: Topic :: Software Development :: Libraries :: Python Modules
Classifier: Intended Audience :: Developers
